{
  "@context": "http://www.w3.org/ns/anno.jsonld",
  "id": "https://archie.demo/voynich-reading/annotations/history/000000001A07B0BHKZPZZ1ANC8.json",
  "type": "AnnotationPage",
  "items": [
    {
      "id": "https://archie.demo/voynich-reading/annotations/000000001A07B0BHKZPZZ1ANC8/v1",
      "type": "Annotation",
      "target": {
        "type": "SpecificResource",
        "source": "https://archie.demo/voynich-reading/canvas/o11",
        "selector": {
          "type": "FragmentSelector",
          "conformsTo": "http://www.w3.org/TR/media-frags/",
          "value": "xywh=pixel:200,160,2300,420"
        }
      },
      "modified": "1970-01-01T00:00:00.042Z",
      "body": [
        {
          "type": "TextualBody",
          "value": "Under the cipher reading, this Latin line is a later owner's attempted key or crib — someone who believed the book was enciphered and jotted a decryption hint.",
          "purpose": "commenting"
        },
        {
          "type": "TextualBody",
          "value": "marginalia",
          "purpose": "tagging"
        },
        {
          "type": "TextualBody",
          "value": "provenance",
          "purpose": "tagging"
        }
      ],
      "archie:logicalId": "000000001A07B0BHKZPZZ1ANC8",
      "archie:rev": "000000001ARD97H215DZCFCC6T",
      "archie:version": 1,
      "archie:lastEditor": "curator",
      "archie:parent": null,
      "archie:reading": "cipher"
    }
  ]
}