{
  "@context": "http://www.w3.org/ns/anno.jsonld",
  "id": "https://archie.demo/voynich/canvas/o1/annotations.json",
  "type": "AnnotationPage",
  "items": [
    {
      "id": "https://archie.demo/voynich/annotations/00000000014H7MXSRX1DT5PK64/v1",
      "type": "Annotation",
      "target": {
        "type": "SpecificResource",
        "source": "https://archie.demo/voynich/canvas/o1",
        "selector": {
          "type": "FragmentSelector",
          "conformsTo": "http://www.w3.org/TR/media-frags/",
          "value": "xywh=pixel:716,220,308,426"
        }
      },
      "modified": "1970-01-01T00:00:00.001Z",
      "body": [
        {
          "type": "TextualBody",
          "value": "The infobox image is folio 68v — one of the cosmological diagrams. Click ahead to page 2 of this project to see the full folio.",
          "purpose": "commenting"
        }
      ],
      "archie:hasHistory": "https://archie.demo/voynich/annotations/history/00000000014H7MXSRX1DT5PK64.json"
    },
    {
      "id": "https://archie.demo/voynich/annotations/000000000227SA2A03KFYFXNYB/v1",
      "type": "Annotation",
      "target": {
        "type": "SpecificResource",
        "source": "https://archie.demo/voynich/canvas/o1",
        "selector": {
          "type": "FragmentSelector",
          "conformsTo": "http://www.w3.org/TR/media-frags/",
          "value": "xywh=pixel:750,2245,265,205"
        }
      },
      "modified": "1970-01-01T00:00:00.002Z",
      "body": [
        {
          "type": "TextualBody",
          "value": "A herbal page reproduced in the article. The unidentified plants are among the manuscript's most-studied features. Page 3 has a higher-resolution scan.",
          "purpose": "commenting"
        }
      ],
      "archie:hasHistory": "https://archie.demo/voynich/annotations/history/000000000227SA2A03KFYFXNYB.json"
    },
    {
      "id": "https://archie.demo/voynich/annotations/0000000003P50MZ62TJXHM1686/v1",
      "type": "Annotation",
      "target": {
        "type": "SpecificResource",
        "source": "https://archie.demo/voynich/canvas/o1",
        "selector": {
          "type": "FragmentSelector",
          "conformsTo": "http://www.w3.org/TR/media-frags/",
          "value": "xywh=pixel:265,80,247,50"
        }
      },
      "modified": "1970-01-01T00:00:00.003Z",
      "body": [
        {
          "type": "TextualBody",
          "value": "**Voynich manuscript** — an illustrated codex written in an unknown script, carbon-dated to the early fifteenth century. The article you're looking at is itself the first page of this demo project.",
          "purpose": "commenting"
        }
      ],
      "archie:hasHistory": "https://archie.demo/voynich/annotations/history/0000000003P50MZ62TJXHM1686.json"
    },
    {
      "id": "https://archie.demo/voynich/annotations/00000000045G61Q8K2AQJFF9TM/v1",
      "type": "Annotation",
      "target": {
        "type": "SpecificResource",
        "source": "https://archie.demo/voynich/canvas/o1",
        "selector": {
          "type": "FragmentSelector",
          "conformsTo": "http://www.w3.org/TR/media-frags/",
          "value": "xywh=pixel:768,2285,24,40"
        }
      },
      "modified": "1970-01-01T00:00:00.004Z",
      "body": [
        {
          "type": "TextualBody",
          "value": "",
          "purpose": "commenting"
        }
      ],
      "archie:hasHistory": "https://archie.demo/voynich/annotations/history/00000000045G61Q8K2AQJFF9TM.json"
    }
  ]
}